{
  "required": true,
  "package": "com.geckolib.mixin",
  "compatibilityLevel": "JAVA_17",
  "refmap": "geckolib.refmap.json",
  "minVersion": "0.8",
  "injectors": {
    "defaultRequire": 1
  },
  "mixins": [
    "com.geckolib.mixin.common.AbstractContainerMenuMixin",
    "com.geckolib.mixin.common.HashedStackMixin",
    "com.geckolib.mixin.common.ItemStackMixin",
    "com.geckolib.mixin.common.LivingEntityMixin",
    "com.geckolib.mixin.common.SynchronizedRemoteSlotMixin"
  ],
  "client": [
    "com.geckolib.mixin.client.BlockEntityRenderStateMixin",
    "com.geckolib.mixin.client.EntityRendererMixin",
    "com.geckolib.mixin.client.EntityRenderStateMixin",
    "com.geckolib.mixin.client.HumanoidArmorLayerMixin",
    "com.geckolib.mixin.client.SpecialModelRenderersMixin",
    "com.geckolib.mixin.client.SpecialModelWrapperMixin",
    "com.geckolib.mixin.client.TextureManagerMixin"
  ]
}
